{
  "label": "",
  "type": "root",
  "children": [
    {
      "label": "unnamed module",
      "type": "UnnamedMo",
      "children": [
        {
          "label": "unnamed package",
          "type": "RootPac",
          "children": [
            {
              "label": "gwt_class_40",
              "type": "Class",
              "children": [
                {
                  "label": "",
                  "type": "Modifiers_Class",
                  "children": [
                    {
                      "label": "public",
                      "type": "Modifier",
                      "children": []
                    }
                  ]
                },
                {
                  "label": "getSomeGWT",
                  "type": "Method",
                  "children": [
                    {
                      "label": "com.google.gwt.user.client.ui.HorizontalPanel",
                      "type": "RETURN_TYPE",
                      "children": []
                    },
                    {
                      "label": "",
                      "type": "Modifiers_Method",
                      "children": [
                        {
                          "label": "private",
                          "type": "Modifier",
                          "children": []
                        }
                      ]
                    },
                    {
                      "label": "pointsLogoPanel",
                      "type": "LocalVariable",
                      "children": [
                        {
                          "label": "com.google.gwt.user.client.ui.HorizontalPanel",
                          "type": "VARIABLE_TYPE",
                          "children": []
                        },
                        {
                          "label": "com.google.gwt.user.client.ui.HorizontalPanel()",
                          "type": "ConstructorCall",
                          "children": []
                        }
                      ]
                    },
                    {
                      "label": "",
                      "type": "For",
                      "children": [
                        {
                          "label": "i",
                          "type": "LocalVariable",
                          "children": [
                            {
                              "label": "int",
                              "type": "VARIABLE_TYPE",
                              "children": []
                            },
                            {
                              "label": "0",
                              "type": "Literal",
                              "children": []
                            }
                          ]
                        },
                        {
                          "label": "LT",
                          "type": "BinaryOperator",
                          "children": [
                            {
                              "label": "i",
                              "type": "VariableRead",
                              "children": []
                            },
                            {
                              "label": "350",
                              "type": "Literal",
                              "children": []
                            }
                          ]
                        },
                        {
                          "label": "POSTINC",
                          "type": "UnaryOperator",
                          "children": [
                            {
                              "label": "i",
                              "type": "VariableWrite",
                              "children": []
                            }
                          ]
                        },
                        {
                          "label": "innerContainer",
                          "type": "LocalVariable",
                          "children": [
                            {
                              "label": "com.google.gwt.user.client.ui.HorizontalPanel",
                              "type": "VARIABLE_TYPE",
                              "children": []
                            },
                            {
                              "label": "com.google.gwt.user.client.ui.HorizontalPanel()",
                              "type": "ConstructorCall",
                              "children": []
                            }
                          ]
                        },
                        {
                          "label": "add",
                          "type": "Invocation",
                          "children": [
                            {
                              "label": "innerContainer",
                              "type": "VariableRead",
                              "children": []
                            },
                            {
                              "label": "com.google.gwt.user.client.ui.Label(java.lang.String)",
                              "type": "ConstructorCall",
                              "children": [
                                {
                                  "label": "\"some GWT text\"",
                                  "type": "Literal",
                                  "children": []
                                }
                              ]
                            }
                          ]
                        },
                        {
                          "label": "add",
                          "type": "Invocation",
                          "children": [
                            {
                              "label": "pointsLogoPanel",
                              "type": "VariableRead",
                              "children": []
                            },
                            {
                              "label": "innerContainer",
                              "type": "VariableRead",
                              "children": []
                            }
                          ]
                        }
                      ]
                    },
                    {
                      "label": "return",
                      "type": "Return",
                      "children": [
                        {
                          "label": "pointsLogoPanel",
                          "type": "VariableRead",
                          "children": []
                        }
                      ]
                    }
                  ]
                },
                {
                  "label": "getSomeGXT",
                  "type": "Method",
                  "children": [
                    {
                      "label": "com.extjs.gxt.ui.client.widget.LayoutContainer",
                      "type": "RETURN_TYPE",
                      "children": []
                    },
                    {
                      "label": "",
                      "type": "Modifiers_Method",
                      "children": [
                        {
                          "label": "private",
                          "type": "Modifier",
                          "children": []
                        }
                      ]
                    },
                    {
                      "label": "pointsLogoPanel",
                      "type": "LocalVariable",
                      "children": [
                        {
                          "label": "com.extjs.gxt.ui.client.widget.LayoutContainer",
                          "type": "VARIABLE_TYPE",
                          "children": []
                        },
                        {
                          "label": "com.extjs.gxt.ui.client.widget.LayoutContainer()",
                          "type": "ConstructorCall",
                          "children": []
                        }
                      ]
                    },
                    {
                      "label": "setLayoutOnChange",
                      "type": "Invocation",
                      "children": [
                        {
                          "label": "pointsLogoPanel",
                          "type": "VariableRead",
                          "children": []
                        },
                        {
                          "label": "true",
                          "type": "Literal",
                          "children": []
                        }
                      ]
                    },
                    {
                      "label": "",
                      "type": "For",
                      "children": [
                        {
                          "label": "i",
                          "type": "LocalVariable",
                          "children": [
                            {
                              "label": "int",
                              "type": "VARIABLE_TYPE",
                              "children": []
                            },
                            {
                              "label": "0",
                              "type": "Literal",
                              "children": []
                            }
                          ]
                        },
                        {
                          "label": "LT",
                          "type": "BinaryOperator",
                          "children": [
                            {
                              "label": "i",
                              "type": "VariableRead",
                              "children": []
                            },
                            {
                              "label": "350",
                              "type": "Literal",
                              "children": []
                            }
                          ]
                        },
                        {
                          "label": "POSTINC",
                          "type": "UnaryOperator",
                          "children": [
                            {
                              "label": "i",
                              "type": "VariableWrite",
                              "children": []
                            }
                          ]
                        },
                        {
                          "label": "innerContainer",
                          "type": "LocalVariable",
                          "children": [
                            {
                              "label": "com.extjs.gxt.ui.client.widget.LayoutContainer",
                              "type": "VARIABLE_TYPE",
                              "children": []
                            },
                            {
                              "label": "com.extjs.gxt.ui.client.widget.LayoutContainer()",
                              "type": "ConstructorCall",
                              "children": []
                            }
                          ]
                        },
                        {
                          "label": "add",
                          "type": "Invocation",
                          "children": [
                            {
                              "label": "pointsLogoPanel",
                              "type": "VariableRead",
                              "children": []
                            },
                            {
                              "label": "innerContainer",
                              "type": "VariableRead",
                              "children": []
                            }
                          ]
                        }
                      ]
                    },
                    {
                      "label": "return",
                      "type": "Return",
                      "children": [
                        {
                          "label": "pointsLogoPanel",
                          "type": "VariableRead",
                          "children": []
                        }
                      ]
                    }
                  ]
                }
              ]
            }
          ]
        }
      ]
    }
  ]
}

